incolumepy.utils-0.9.3-py3.5-nspkg.pth
incolumepy/utils/__init__.py
incolumepy/utils/fake_cpf.py
incolumepy/utils/files.py
incolumepy/utils/sequencia.py
incolumepy/utils/utils.py
incolumepy/utils/version.txt
incolumepy.utils-0.9.3.dist-info/METADATA
incolumepy.utils-0.9.3.dist-info/RECORD
incolumepy.utils-0.9.3.dist-info/WHEEL
incolumepy.utils-0.9.3.dist-info/entry_points.txt
incolumepy.utils-0.9.3.dist-info/namespace_packages.txt
incolumepy.utils-0.9.3.dist-info/top_level.txt
