Metadata-Version: 2.1
Name: incolumepy.utils
Version: 0.9.3
Summary: package incolumepy utils
Home-page: http://www.incolume.com.br
Author: @britodfbr
Author-email: contato@incolume.com.br
License: BSD
Keywords: python utils incolumepy
Platform: UNKNOWN
Classifier: Development Status :: 5 - Production/Stable
Classifier: Operating System :: OS Independent
Classifier: Natural Language :: Portuguese (Brazilian)
Classifier: Programming Language :: Python
Classifier: Topic :: Software Development :: Libraries :: Python Modules
Classifier: Topic :: Utilities
Requires-Dist: setuptools
Requires-Dist: pytest
Requires-Dist: nose
Requires-Dist: rstr
